[
    {
        "id_baliza": 1,
        "marca_baliza": "PMK Grupo",
        "modelo": "30101",
        "Fabricante": "Yuyao Jiming Electronic Co., Ltd",
        "Origen": "China",
        "Actuación_realizada_en_España": "Distribución",
        "precio_venta": 49.9,
        "alimentacion": "3x AA",
        "numero_pilas": 3,
        "marca_pilas": "Sin Marca",
        "tipo_pila": "AA",
        "precio_por_pila": {
            "precio": 0.28,
            "fuente": "AliExpress, Shein, bazares multiprecio"
        },
        "factor_sulfatacion": {
            "tasa_anual": 0.0105,
            "fuente": "Crowdsourced Device Damage Reports"
        },
        "desconectable": "No",
        "funda_termica": "No",
        "imagen": "PMK_Grupo.png",
        "fabricante": "Yuyao Jiming Electronic Co. Ltd",
        "origen": "China",
        "titulo_imagen": "PMK_Grupo.png",
        "quality_5": 3,
        "value_5": 3.1,
        "imagen_url": "/comparativa-balizas-mvp/client/images/beacons/PMK_Grupo.png",
        "Resistencia": "IP54",
        "Operador": "Telefónica Tech",
        "Piloto_Gps": "No",
        "Aplicación_Móvil": "No Integrada",
        "Fiabilidad": "3.0",
        "Autonomia": "2.9",
        "Conectividad": "3.3",
        "Calidad_Precio": "3.1",
        "funcion_1": "Homologación como V16 Conecta",
        "funcion_2": "con conexión DGT 3.0",
        "funcion_3": "Aplicación Móvil no integrada",
        "funcion_4": "Alcance 360º",
        "funcion_5": "resistencia 180Pa",
        "funcion_6": "baterías 9V",
        "funcion_7": "Magnetismo Nmodio",
        "ventaja_1": "Tienda PMK Grupo en Betxi.",
        "ventaja_2": "B2C sin registro.",
        "ventaja_3": "Precios con descuentos por packs hasta 32 unidades.",
        "ventaja_4": "Presencia fuerte en Amazon.",
        "ventaja_5": "Información sobre stock disponible",
        "inconveniente_1": "Fabricado en China.",
        "inconveniente_2": "No información sobre B2C",
        "inconveniente_3": "B2B",
        "inconveniente_4": "garantías",
        "inconveniente_5": "pedidos etc...",
        "inconveniente_6": "No tiene botón señal envío de datos."
    },
    {
        "id_baliza": 2,
        "marca_baliza": "SOS Flash V16 Connected",
        "modelo": "BAL/2",
        "Fabricante": "Yuyao Jiming Electronic Co., Ltd",
        "Origen": "China",
        "Actuación_realizada_en_España": "Distribución",
        "precio_venta": 49.9,
        "alimentacion": "3x AAA",
        "numero_pilas": 3,
        "marca_pilas": "Sin Marca",
        "tipo_pila": "AAA",
        "precio_por_pila": {
            "precio": 0.2,
            "fuente": "AliExpress, Shein, bazares multiprecio"
        },
        "factor_sulfatacion": {
            "tasa_anual": 0.0105,
            "fuente": "User-Reported Failure Rates"
        },
        "desconectable": "No",
        "funda_termica": "No",
        "imagen": "SOS_Flash_Connected.png",
        "fabricante": "Yuyao Jiming Electronic Co. Ltd",
        "origen": "China",
        "titulo_imagen": "SOS_Flash_Connected.png",
        "quality_5": 3.6,
        "value_5": 3.5,
        "imagen_url": "/comparativa-balizas-mvp/client/images/beacons/SOS_Flash_Connected.png",
        "Resistencia": "IP54",
        "Operador": "Telefonica Tech",
        "Piloto_Gps": "No",
        "Aplicación_Móvil": "Inspide",
        "Fiabilidad": "3.6",
        "Autonomia": "3.2",
        "Conectividad": "3.7",
        "Calidad_Precio": "3.5",
        "funcion_1": "Homologación como V16 Conecta",
        "funcion_2": "con conexión DGT 3.0",
        "funcion_3": "Aplicación Móvil Inspide",
        "funcion_4": "Alcance 360º",
        "funcion_5": "resistencia 180Pa",
        "funcion_6": "baterías AA+ x3 y magnetismo Imán Nodimio",
        "ventaja_1": "Acceso a todas la balizas a través de Inspide por Whatsapp.",
        "ventaja_2": "Soporte Ventosa para Baliza por 5.9€"
    },
    {
        "id_baliza": 3,
        "marca_baliza": "Flash Mate",
        "modelo": "Beacon Light IoT",
        "Fabricante": "Ningbo Tianqi Intelligent Technology Co., Ltd",
        "Origen": "China",
        "Actuación_realizada_en_España": "Distribución",
        "precio_venta": 49.99,
        "alimentacion": "3x AA",
        "numero_pilas": 3,
        "marca_pilas": "Maxell",
        "tipo_pila": "AA",
        "precio_por_pila": {
            "precio": 0.6,
            "fuente": "Amazon, MediaMarkt, Farnell, RS Components"
        },
        "factor_sulfatacion": {
            "tasa_anual": 0.0095,
            "fuente": "Maxell LR03 datasheet (biz.maxell.com)"
        },
        "desconectable": "Si",
        "funda_termica": "Tela",
        "imagen": "Flash_Mate.png",
        "fabricante": "Ningbo Tianqi Intelligent Technology Co. Ltd",
        "origen": "China",
        "titulo_imagen": "Flash_Mate.png",
        "quality_5": 3.44,
        "value_5": 3.13,
        "imagen_url": "/comparativa-balizas-mvp/client/images/beacons/Flash_Mate.png",
        "Resistencia": "IP54",
        "funcion_1": "Homologación como V16 Conecta",
        "funcion_2": "con conexión DGT 3.0",
        "funcion_3": "Aplicación Móvil Inspide",
        "funcion_4": "Alcance 360º",
        "funcion_5": "resistencia 180Pa",
        "funcion_6": "baterías AA+ x3 y magnetismo Imán Nodimio"
    },
    {
        "id_baliza": 4,
        "marca_baliza": "Light Mup beacon",
        "modelo": "Beacon Light IoT",
        "Fabricante": "Ningbo Tianqi Intelligent Technology Co., Ltd",
        "Origen": "China",
        "Actuación_realizada_en_España": "Distribución",
        "precio_venta": 46,
        "alimentacion": "3x AA",
        "numero_pilas": 3,
        "marca_pilas": "Maxell",
        "tipo_pila": "AA",
        "precio_por_pila": {
            "precio": 0.6,
            "fuente": "Amazon, MediaMarkt, Farnell, RS Components"
        },
        "factor_sulfatacion": {
            "tasa_anual": 0.0095,
            "fuente": "Maxell LR03 datasheet (biz.maxell.com)"
        },
        "desconectable": "No",
        "funda_termica": "Tela",
        "imagen": "Light_Mup_beacon.png",
        "fabricante": "Ningbo Tianqi Intelligent Technology Co. Ltd",
        "origen": "China",
        "titulo_imagen": "Light_Mup_beacon.png",
        "quality_5": 3.44,
        "value_5": 3.74,
        "imagen_url": "/comparativa-balizas-mvp/client/images/beacons/Light_Mup_beacon.png",
        "Resistencia": "IP54",
        "Piloto_Gps": "No",
        "Aplicación_Móvil": "No",
        "Fiabilidad": "4.3",
        "Autonomia": "3.0",
        "Conectividad": "3.5",
        "Calidad_Precio": "3.9",
        "funcion_1": "Homologación como V16 Conecta",
        "funcion_2": "con conexión DGT 3.00",
        "funcion_3": "Aplicación Móvil no Integrada",
        "funcion_4": "Alcance 360º",
        "funcion_5": "resistencia 180Pa",
        "funcion_6": "baterías AA+ 3x LR6 y magnetismo Imán Nodimio",
        "ventaja_1": "Lomisa Distribuciones y Proyectos s.l.u. distribuidora de productos y soluciones de ingeniería.",
        "ventaja_2": "Microsite muy completa.",
        "ventaja_3": "Catálogo de producto específico compuesto de Balizas en tres colores (rojo, azul y amarillo)",
        "ventaja_4": "fundas",
        "ventaja_5": "cable de emergencia",
        "ventaja_6": "guante y chaleco",
        "ventaja_7": "y base adherente de 8cm para superficies no ferrosas.",
        "inconveniente_1": "Venta a través de Amazon.",
        "inconveniente_2": "Enlace con QR para ver el Estado de la Baliza y comprobar carga y vida útil."
    },
    {
        "id_baliza": 5,
        "marca_baliza": "Uirax V16 2.0 IoT",
        "modelo": "Beacon Light IoT",
        "Fabricante": "Ningbo Tianqi Intelligent Technology Co., Ltd",
        "Origen": "China",
        "Actuación_realizada_en_España": "Distribución",
        "precio_venta": 39.99,
        "alimentacion": "3x AA",
        "numero_pilas": 3,
        "marca_pilas": "Maxell",
        "tipo_pila": "AA",
        "precio_por_pila": {
            "precio": 0.6,
            "fuente": "Amazon, MediaMarkt, Farnell, RS Components"
        },
        "factor_sulfatacion": {
            "tasa_anual": 0.0095,
            "fuente": "Maxell LR03 datasheet (biz.maxell.com)"
        },
        "desconectable": "No",
        "funda_termica": "No",
        "imagen": "Uirax_V16_2.0_IoT.png",
        "fabricante": "Ningbo Tianqi Intelligent Technology Co. Ltd",
        "origen": "China",
        "titulo_imagen": "Uirax_V16_2.0_IoT.png",
        "quality_5": 3.29,
        "value_5": 4.11,
        "imagen_url": "/comparativa-balizas-mvp/client/images/beacons/Uirax_V16_2.0_IoT.png",
        "Resistencia": "IP54",
        "Operador": "Telefonica Tech",
        "Piloto_Gps": "No",
        "Aplicación_Móvil": "No",
        "Fiabilidad": "3.0",
        "Autonomia": "3.0",
        "Conectividad": "3.0",
        "Calidad_Precio": "3.0",
        "funcion_1": "Homologación como V16 Conecta",
        "funcion_2": "con conexión DGT 3.0",
        "funcion_3": "Aplicación Móvil Inspide",
        "funcion_4": "Alcance 360º",
        "funcion_5": "resistencia 180Pa",
        "funcion_6": "baterías AA+ x3 y magnetismo Imán Nodimio",
        "ventaja_1": "Proveedor de Luminaria LED.",
        "inconveniente_1": "Made in China.",
        "inconveniente_2": "Sólo pedidos de grandes volúmenes.",
        "inconveniente_3": "No B2C",
        "inconveniente_4": "no política de precios."
    },
    {
        "id_baliza": 6,
        "marca_baliza": "Baliza V16 Geolocalizada Kia",
        "modelo": "Beacon Light IoT CH-009",
        "Fabricante": "Ningbo Chakesi Electronic Co., Ltd",
        "Origen": "China",
        "Actuación_realizada_en_España": "Distribución",
        "precio_venta": 48.96,
        "alimentacion": "3x AA",
        "numero_pilas": 3,
        "marca_pilas": "Sin Marca",
        "tipo_pila": "AA",
        "precio_por_pila": {
            "precio": 0.28,
            "fuente": "AliExpress, Shein, bazares multiprecio"
        },
        "factor_sulfatacion": {
            "tasa_anual": 0.0105,
            "fuente": "Crowdsourced Device Damage Reports"
        },
        "desconectable": "Si",
        "funda_termica": "Tela",
        "imagen": "Baliza_V16_Geolocalizada_Kia.png",
        "fabricante": "Ningbo Chakesi Electronic Co. Ltd",
        "origen": "China",
        "titulo_imagen": "Baliza_V16_Geolocalizada_Kia.png",
        "quality_5": 2.65,
        "value_5": 2.7,
        "imagen_url": "/comparativa-balizas-mvp/client/images/beacons/Baliza_V16_Geolocalizada_Kia.png",
        "Resistencia": "IP54",
        "funcion_1": "Homologación como V16 Conecta",
        "funcion_2": "con conexión DGT 3.0",
        "funcion_3": "Aplicación Móvil Inspide",
        "funcion_4": "Alcance 360º",
        "funcion_5": "resistencia 180Pa",
        "funcion_6": "baterías AA+ x3 y magnetismo Imán Nodimio",
        "ventaja_1": "Proveedor de Luminaria LED."
    },
    {
        "id_baliza": 7,
        "marca_baliza": "Geobaliza beacon V16",
        "modelo": "Beacon Light IoT CH-009",
        "Fabricante": "Ningbo Chakesi Electronic Co., Ltd",
        "Origen": "China",
        "Actuación_realizada_en_España": "Distribución",
        "precio_venta": 38.9,
        "alimentacion": "3x AAA",
        "numero_pilas": 3,
        "marca_pilas": "Sin Marca",
        "tipo_pila": "AAA",
        "precio_por_pila": {
            "precio": 0.2,
            "fuente": "AliExpress, Shein, bazares multiprecio"
        },
        "factor_sulfatacion": {
            "tasa_anual": 0.0105,
            "fuente": "User-Reported Failure Rates"
        },
        "desconectable": "No",
        "funda_termica": "No",
        "imagen": "Geobaliza_beacon_V16.png",
        "fabricante": "Ningbo Chakesi Electronic Co. Ltd",
        "origen": "China",
        "titulo_imagen": "Geobaliza_beacon_V16.png",
        "Resistencia": "IP54",
        "Piloto_Gps": "No",
        "Aplicación_Móvil": "No",
        "Fiabilidad": "3.2",
        "Autonomia": "3.0",
        "Conectividad": "3.5",
        "Calidad_Precio": "4.0",
        "funcion_1": "Homologación como V16 Conecta",
        "funcion_2": "con conexión DGT 3.0",
        "funcion_3": "Aplicación Móvil Inspide",
        "funcion_4": "Alcance 360º",
        "funcion_5": "resistencia 180Pa",
        "funcion_6": "baterías AA+ x3 y magnetismo Imán Nodimio",
        "ventaja_1": "Microsite específica para balizas bien estructurada.",
        "ventaja_2": "B2C con posibilidad de compra y entrega",
        "ventaja_3": "Código de márketing 15% de descuento con reserva",
        "inconveniente_1": "Producto Chino que se pide por lotes grandes condicionado a transporte marítimo y posible variación aranceles.",
        "inconveniente_2": "Falta concretar garantía de fabricante y Postventa.",
        "inconveniente_3": "AA 3+ con riesgo de sulfatado.",
        "imagen_url": "/comparativa-balizas-mvp/client/images/beacons/Geobaliza_beacon_V16.png"
    },
    {
        "id_baliza": 8,
        "marca_baliza": "Baliza V16 IoT Aldi",
        "modelo": "DP-EL2022-C1",
        "Fabricante": "Distribuciones Escudero Fijo, S. L.",
        "Origen": "China",
        "Actuación_realizada_en_España": "Distribución",
        "precio_venta": 39.99,
        "alimentacion": "3x AA",
        "numero_pilas": 3,
        "marca_pilas": "Sin Marca",
        "tipo_pila": "AA",
        "precio_por_pila": {
            "precio": 0.28,
            "fuente": "AliExpress, Shein, bazares multiprecio"
        },
        "factor_sulfatacion": {
            "tasa_anual": 0.0105,
            "fuente": "Crowdsourced Device Damage Reports"
        },
        "desconectable": "No",
        "funda_termica": "No",
        "imagen": "Baliza_V16_IoT_Aldi.png",
        "fabricante": "Distribuciones Escudero Fijo S. L.",
        "origen": "China",
        "titulo_imagen": "Baliza_V16_IoT_Aldi.png",
        "quality_5": 2,
        "value_5": 2.5,
        "imagen_url": "/comparativa-balizas-mvp/client/images/beacons/Baliza_V16_IoT_Aldi.png",
        "Resistencia": "IP54",
        "funcion_1": "Homologación como V16 Conecta",
        "funcion_2": "con conexión DGT 3.0",
        "funcion_3": "Aplicación Móvil Inspide",
        "funcion_4": "Alcance 360º",
        "funcion_5": "resistencia 180Pa",
        "funcion_6": "baterías AA+ x3 y magnetismo Imán Nodimio"
    },
    {
        "id_baliza": 9,
        "marca_baliza": "NK SOS Road Connected",
        "modelo": "DP-EL2022-C1",
        "Fabricante": "Distribuciones Escudero Fijo, S. L.",
        "Origen": "China",
        "Actuación_realizada_en_España": "Distribución",
        "precio_venta": 49.99,
        "alimentacion": "3x AA",
        "numero_pilas": 3,
        "marca_pilas": "Sin Marca",
        "tipo_pila": "AA",
        "precio_por_pila": {
            "precio": 0.28,
            "fuente": "AliExpress, Shein, bazares multiprecio"
        },
        "factor_sulfatacion": {
            "tasa_anual": 0.0105,
            "fuente": "Crowdsourced Device Damage Reports"
        },
        "desconectable": "No",
        "funda_termica": "No",
        "imagen": "NK_SOS_Road_Connected.png",
        "fabricante": "Distribuciones Escudero Fijo S. L.",
        "origen": "China",
        "titulo_imagen": "NK_SOS_Road_Connected.png",
        "quality_5": 2,
        "value_5": 2.06,
        "imagen_url": "/comparativa-balizas-mvp/client/images/beacons/NK_SOS_Road_Connected.png",
        "Resistencia": "IP54",
        "Operador": "Orange",
        "Piloto_Gps": "No",
        "Aplicación_Móvil": "No",
        "Fiabilidad": "3.0",
        "Autonomia": "3.0",
        "Conectividad": "3.0",
        "Calidad_Precio": "3.0",
        "funcion_1": "Homologación como V16 Conectada",
        "funcion_2": "con conexión DGT 3.0 Aplicación Móvil (No)",
        "funcion_3": "Alcance 360º",
        "funcion_4": "resistencia 180Pa",
        "funcion_5": "baterías AA+ x3 y magnetismo Imán Nodimio",
        "ventaja_1": "Ensamblado en España",
        "inconveniente_1": "Fabricado en China",
        "inconveniente_2": "Falta de canal B2C"
    },
    {
        "id_baliza": 10,
        "marca_baliza": "EmergLight Geo IoT",
        "modelo": "EmergLight X",
        "Fabricante": "Yuyao Jiming Electronic Co., Ltd",
        "Origen": "China",
        "Actuación_realizada_en_España": "Distribución",
        "precio_venta": 43.95,
        "alimentacion": "3x AA",
        "numero_pilas": 3,
        "marca_pilas": "Sin Marca",
        "tipo_pila": "AA",
        "precio_por_pila": {
            "precio": 0.28,
            "fuente": "AliExpress, Shein, bazares multiprecio"
        },
        "factor_sulfatacion": {
            "tasa_anual": 0.0105,
            "fuente": "Crowdsourced Device Damage Reports"
        },
        "desconectable": "No",
        "funda_termica": "No",
        "imagen": "EmergLight_Geo_IoT.png",
        "fabricante": "Yuyao Jiming Electronic Co. Ltd",
        "origen": "China",
        "titulo_imagen": "EmergLight_Geo_IoT.png",
        "quality_5": 2,
        "value_5": 2.27,
        "imagen_url": "/comparativa-balizas-mvp/client/images/beacons/EmergLight_Geo_IoT.png",
        "Resistencia": "IP54",
        "Operador": "Telefonica Tech",
        "Piloto_Gps": "No",
        "Aplicación_Móvil": "No",
        "Fiabilidad": "3.0",
        "Autonomia": "3.0",
        "Conectividad": "3.0",
        "Calidad_Precio": "3.0",
        "funcion_1": "Homologación como V16 Conecta",
        "funcion_2": "con conexión DGT 3.0",
        "funcion_3": "Aplicación Móvil No Integrada Alcance 360º",
        "funcion_4": "resistencia 180Pa",
        "funcion_5": "baterías AA+ x3 y magnetismo Imán Nodimio",
        "ventaja_1": "Distribuidor Cantabro (Camargo).",
        "ventaja_2": "Microsite para la venta del producto.",
        "ventaja_3": "Cupón descuento",
        "ventaja_4": "B2C directo con propuesta de descuento desde 5€",
        "inconveniente_1": "Made in China.",
        "inconveniente_2": "Gastos de transporte 6,5€",
        "inconveniente_3": "3 pilas AA+. Riesgo Sulfatado"
    },
    {
        "id_baliza": 11,
        "marca_baliza": "Fase Light V16",
        "modelo": "Faselight IOT",
        "Fabricante": "Ningbo Yinzhou Wilton Autoparts",
        "Origen": "China",
        "Actuación_realizada_en_España": "Distribución",
        "precio_venta": 45.99,
        "alimentacion": "4x AAA",
        "numero_pilas": 4,
        "marca_pilas": "Marca Blanca",
        "tipo_pila": "AAA",
        "precio_por_pila": {
            "precio": 0.38,
            "fuente": "Distribuidores OEM y marketplaces nacionales"
        },
        "factor_sulfatacion": {
            "tasa_anual": 0.0125,
            "fuente": "OEM Leakage Tests"
        },
        "desconectable": "No",
        "funda_termica": "No",
        "imagen": "Fase_Light_V16.png",
        "fabricante": "Ningbo Yinzhou Wilton Autoparts",
        "origen": "China",
        "titulo_imagen": "Fase_Light_V16.png",
        "quality_5": 3.45,
        "value_5": 3.8,
        "imagen_url": "/comparativa-balizas-mvp/client/images/beacons/Fase_Light_V16.png",
        "Resistencia": "IP54",
        "Operador": "Telefonica Tech",
        "Piloto_Gps": "No",
        "Aplicación_Móvil": "Sos Alert",
        "Fiabilidad": "4.2",
        "Autonomia": "3.3",
        "Conectividad": "3.5",
        "Calidad_Precio": "3.9",
        "funcion_1": "Homologación como V16 Conecta con conexión DGT 3.00",
        "funcion_2": "Alcance 360º",
        "funcion_3": "resistencia 180Pa",
        "funcion_4": "baterías AAA y magnetismo Imán Nodimio",
        "ventaja_1": "Buen marketing en la web",
        "ventaja_2": "Los acabados de goma ayudan a la protección de la baliza",
        "ventaja_3": "Buen material audiovisual",
        "ventaja_4": "Reflector diseñado por la Complutense",
        "inconveniente_1": "Acabados en plástico se llevan mal con el calor extremo.",
        "inconveniente_2": "No avisador de señal GPS encendido.",
        "inconveniente_3": "Intensidad de luz Led lejos del nivel esperado. No se informa",
        "inconveniente_4": "Mucho enfoque en Amazon",
        "inconveniente_5": "Fabricación en China.Producto muyy chino",
        "inconveniente_6": "Accesorios no incluidos en el precio"
    },
    {
        "id_baliza": 12,
        "marca_baliza": "FlashLED SOS V16",
        "modelo": "FlashLED SOS",
        "Fabricante": "Kepar Electrónica, Zaragoza",
        "Origen": "España",
        "Actuación_realizada_en_España": "Ensamblaje",
        "precio_venta": 49.9,
        "alimentacion": "1x 9V",
        "numero_pilas": 1,
        "marca_pilas": "Marca Blanca",
        "tipo_pila": "9V",
        "precio_por_pila": {
            "precio": 1.3,
            "fuente": "Distribuidores OEM y marketplaces nacionales"
        },
        "factor_sulfatacion": {
            "tasa_anual": 0.0125,
            "fuente": "Independent Lab Tests (2023)"
        },
        "desconectable": "No",
        "funda_termica": "No",
        "imagen": "FlashLED_SOS_V16.png",
        "fabricante": "Kepar Electrónica Zaragoza",
        "origen": "España",
        "titulo_imagen": "FlashLED_SOS_V16.png",
        "quality_5": 3.87,
        "value_5": 3.65,
        "imagen_url": "/comparativa-balizas-mvp/client/images/beacons/FlashLED_SOS_V16.png",
        "Resistencia": "IP54",
        "Operador": "Telefonica Tech",
        "Piloto_Gps": "No",
        "Aplicación_Móvil": "SoS Alert",
        "Fiabilidad": "3.9",
        "Autonomia": "4.2",
        "Conectividad": "4.0",
        "Calidad_Precio": "3.8",
        "funcion_1": "Homologación como V16 Conectada",
        "funcion_2": "con conexión DGT 3.0 Aplicación Móvil (No)",
        "funcion_3": "Alcance 360º",
        "funcion_4": "resistencia 180Pa",
        "funcion_5": "baterías AA+ x3 y magnetismo Imán Nodimio",
        "ventaja_1": "Accesorios a parte del precio, kit Emergencia V16, Chaleco, Funda Rigida.",
        "ventaja_2": "Extensa Base de Clientes.",
        "ventaja_3": "Certificación EUIPO.",
        "ventaja_4": "Web muy completa.",
        "inconveniente_1": "9V no desconectable.",
        "inconveniente_2": "No avisador de señal GPS encendido.",
        "inconveniente_3": "60 candelas Intensidad de luz Led lejos del nivel esperado",
        "inconveniente_4": "Versión similar a la Obsoleta de Help Flash. Modelo tipo de Kepar",
        "inconveniente_5": "Ensamblaje en Zaragoza. Materiales Chinos",
        "inconveniente_6": "Controversia con Turisport y KP Sport en concurso acreedores"
    },
    {
        "id_baliza": 13,
        "marca_baliza": "Hero Driver",
        "modelo": "HD V16.IoT",
        "Fabricante": "Shenzhen Well-Done Industrial Co., Ltd",
        "Origen": "China",
        "Actuación_realizada_en_España": "Distribución",
        "precio_venta": 49.9,
        "alimentacion": "1x 9V",
        "numero_pilas": 1,
        "marca_pilas": "Sin Marca",
        "tipo_pila": "9V",
        "precio_por_pila": {
            "precio": 0.8,
            "fuente": "AliExpress, Shein, bazares multiprecio"
        },
        "factor_sulfatacion": {
            "tasa_anual": 0.0105,
            "fuente": "Empirical Data from Repair Shops"
        },
        "desconectable": "No",
        "funda_termica": "No",
        "imagen": "Hero_Driver.png",
        "fabricante": "Shenzhen Well-Done Industrial Co. Ltd",
        "origen": "China",
        "titulo_imagen": "Hero_Driver.png",
        "quality_5": 2,
        "value_5": 2.06,
        "imagen_url": "/comparativa-balizas-mvp/client/images/beacons/Fase_Light_V16.png",
        "Resistencia": "IP54",
        "Piloto_Gps": "No",
        "Aplicación_Móvil": "No",
        "Fiabilidad": "3.0",
        "Autonomia": "3.0",
        "Conectividad": "3.0",
        "Calidad_Precio": "3.0",
        "funcion_1": "Homologación como V16 Conecta",
        "funcion_2": "con conexión DGT 3.0",
        "funcion_3": "Aplicación Móvil No Integrada Alcance 360º",
        "funcion_4": "resistencia 180Pa",
        "funcion_5": "baterías AA+ x3 y magnetismo Imán Nodimio"
    },
    {
        "id_baliza": 14,
        "marca_baliza": "Help Flash IoT",
        "modelo": "Help Flash IoT",
        "Fabricante": "Kepar Electrónica S. L.",
        "Origen": "España",
        "Actuación_realizada_en_España": "Ensamblaje",
        "precio_venta": 49.95,
        "alimentacion": "4x AAA",
        "numero_pilas": 4,
        "marca_pilas": "Marca Blanca",
        "tipo_pila": "AAA",
        "precio_por_pila": {
            "precio": 0.38,
            "fuente": "Distribuidores OEM y marketplaces nacionales"
        },
        "factor_sulfatacion": {
            "tasa_anual": 0.0125,
            "fuente": "OEM Leakage Tests"
        },
        "desconectable": "No",
        "funda_termica": "No",
        "imagen": "Help_Flash_IoT.png",
        "fabricante": "Kepar Electrónica S. L.",
        "origen": "España",
        "titulo_imagen": "Help_Flash_IoT.png",
        "quality_5": 2.86,
        "value_5": 3.39,
        "imagen_url": "/comparativa-balizas-mvp/client/images/beacons/Help_Flash_IoT_9V.png",
        "Resistencia": "IP54",
        "Operador": "Vodafone",
        "Piloto_Gps": "No",
        "Aplicación_Móvil": "No",
        "Fiabilidad": "4.0",
        "Autonomia": "4.0",
        "Conectividad": "3.5",
        "Calidad_Precio": "4.0",
        "funcion_1": "Homologación como V16 Conecta",
        "funcion_2": "con conexión DGT 3.0",
        "funcion_3": "Aplicación Móvil gratuita para conectar con la aseguradora",
        "funcion_4": "Alcance 360º",
        "funcion_5": "resistencia 180Pa",
        "funcion_6": "baterías 9V",
        "funcion_7": "Magnetismo Imán Nodimio",
        "ventaja_1": "Distribuidor solvente español.",
        "ventaja_2": "Extensa Base de Clientes.",
        "ventaja_3": "Recomendado por Ponle Freno.",
        "ventaja_4": "Muchos acuerdos con distribuidores.",
        "inconveniente_1": "9V o AA+ 3 Pilas según el dispositivo.",
        "inconveniente_2": "No avisador de señal GPS encendido.",
        "inconveniente_3": "Intensidad de luz Led lejos del nivel esperado",
        "inconveniente_4": "Versiones Obsoletas. Catalogo Incierto",
        "inconveniente_5": "Ensamblaje en Zaragoza. Materiales Chinos",
        "inconveniente_6": "No informa Candelas"
    },
    {
        "id_baliza": 15,
        "marca_baliza": "Helios v16 beacon",
        "modelo": "HV16.1",
        "Fabricante": "Ningbo Chakesi Electronic Co., Ltd",
        "Origen": "China",
        "Actuación_realizada_en_España": "Distribución",
        "precio_venta": 39.9,
        "alimentacion": "3x AA",
        "numero_pilas": 3,
        "marca_pilas": "Sin Marca",
        "tipo_pila": "AA",
        "precio_por_pila": {
            "precio": 0.28,
            "fuente": "AliExpress, Shein, bazares multiprecio"
        },
        "factor_sulfatacion": {
            "tasa_anual": 0.0105,
            "fuente": "Crowdsourced Device Damage Reports"
        },
        "desconectable": "No",
        "funda_termica": "No",
        "imagen": "Helios_v16_beacon.png",
        "fabricante": "Ningbo Chakesi Electronic Co. Ltd",
        "origen": "China",
        "titulo_imagen": "Helios_v16_beacon.png",
        "quality_5": 2,
        "value_5": 2.06,
        "imagen_url": "/comparativa-balizas-mvp/client/images/beacons/Helios_v16_beacon.png",
        "Resistencia": "IP65",
        "Operador": "Telefonica Tech",
        "Piloto_Gps": "No",
        "Aplicación_Móvil": "No",
        "Fiabilidad": "4.5",
        "Autonomia": "3.0",
        "Conectividad": "4.5",
        "Calidad_Precio": "4.5",
        "funcion_1": "Homologación como V16 Conecta",
        "funcion_2": "con conexión DGT 3.0",
        "funcion_3": "Aplicación Móvil",
        "funcion_4": "Alcance 360º",
        "funcion_5": "resistencia 180Pa",
        "funcion_6": "baterías y magnetismo Imán Nodimio",
        "ventaja_1": "Soportado por Foxconn en última instancia.",
        "ventaja_2": "Ratio Calidad/Precio imbatible.",
        "ventaja_3": "Incluye un cargador adicional para asegurar que siempre esté listo.",
        "ventaja_4": "Máxima Resistencia y Conectividad.",
        "ventaja_5": "Multioperador para garantizar la señal.",
        "ventaja_6": "B2C con demora en la entrega.",
        "ventaja_7": "Código Promocional",
        "inconveniente_1": "Entregas diferidas hasta el 1 de julio.",
        "inconveniente_2": "Fabricado en China y pre-órdenes.",
        "inconveniente_3": "No informa Candelas"
    },
    {
        "id_baliza": 16,
        "marca_baliza": "Hella V16",
        "modelo": "HV16.1",
        "Fabricante": "Kepar Electrónica S. L.",
        "Origen": "España",
        "Actuación_realizada_en_España": "Ensamblaje",
        "precio_venta": 54.95,
        "alimentacion": "1x 9V",
        "numero_pilas": 1,
        "marca_pilas": "Varta",
        "tipo_pila": "9V",
        "precio_por_pila": {
            "precio": 2.1,
            "fuente": "Varta oficial y minoristas europeos"
        },
        "factor_sulfatacion": {
            "tasa_anual": 0.0085,
            "fuente": "Varta Long-Term Storage Study (2019)"
        },
        "desconectable": "No",
        "funda_termica": "No",
        "imagen": "Hella_V16.png",
        "fabricante": "Kepar Electrónica S. L.",
        "origen": "España",
        "titulo_imagen": "Hella_V16.png",
        "quality_5": 4.01,
        "value_5": 3.85,
        "imagen_url": "/comparativa-balizas-mvp/client/images/beacons/Hella_V16.png",
        "Resistencia": "IP54",
        "Operador": "Vodafone",
        "Piloto_Gps": "No",
        "Aplicación_Móvil": "No",
        "Fiabilidad": "4.0",
        "Autonomia": "3.6",
        "Conectividad": "3.0",
        "Calidad_Precio": "4.1",
        "funcion_1": "Homologación como V16 Conecta",
        "funcion_2": "con conexión DGT 3.0",
        "funcion_3": "No se especifica ninguna Aplicación Móvil",
        "funcion_4": "Alcance 360º",
        "funcion_5": "resistencia 180Pa",
        "funcion_6": "baterías y magnetismo Imán Nodimio",
        "ventaja_1": "Proveedor Top del mundo de la Automoción",
        "ventaja_2": "Video Integrado en la web https://www.hella-v16.com",
        "inconveniente_1": "No se especifica APP.",
        "inconveniente_2": "No se especifican precios.",
        "inconveniente_3": "No B2C para compra on line. Posiblemente a través de distribuidores o talleres.",
        "inconveniente_4": "No informa Candelas"
    },
    {
        "id_baliza": 17,
        "marca_baliza": "iWottoLight IoT",
        "modelo": "IWottoLight IoT",
        "Fabricante": "Ningbo Shenglin Electric Appliance Co., Ltd",
        "Origen": "China",
        "Actuación_realizada_en_España": "Distribución",
        "precio_venta": 39.99,
        "alimentacion": "3x AAA",
        "numero_pilas": 3,
        "marca_pilas": "Sin Marca",
        "tipo_pila": "AAA",
        "precio_por_pila": {
            "precio": 0.2,
            "fuente": "AliExpress, Shein, bazares multiprecio"
        },
        "factor_sulfatacion": {
            "tasa_anual": 0.0105,
            "fuente": "User-Reported Failure Rates"
        },
        "desconectable": "No",
        "funda_termica": "No",
        "imagen": "iWottoLight_IoT.png",
        "fabricante": "Ningbo Shenglin Electric Appliance Co. Ltd",
        "origen": "China",
        "titulo_imagen": "iWottoLight_IoT.png",
        "quality_5": 2,
        "value_5": 2.5,
        "imagen_url": "/comparativa-balizas-mvp/client/images/beacons/iWottoLight_IoT.png",
        "Resistencia": "IP54",
        "Operador": "Vodafone",
        "Piloto_Gps": "No",
        "Aplicación_Móvil": "No",
        "Fiabilidad": "4.0",
        "Autonomia": "4.0",
        "Conectividad": "3.5",
        "Calidad_Precio": "4.0",
        "funcion_1": "Homologación como V16 Conecta",
        "funcion_2": "con conexión DGT 3.0",
        "funcion_3": "Aplicación Móvil gratuita para conectar con la aseguradora",
        "funcion_4": "Alcance 360º",
        "funcion_5": "resistencia 180Pa",
        "funcion_6": "baterías 9V",
        "funcion_7": "Magnetismo Imán Nodimio"
    },
    {
        "id_baliza": 18,
        "marca_baliza": "Ledone Connected",
        "modelo": "Ledone Connected /Erum Vial",
        "Fabricante": "Plásticos Erum, s.l., Alcoy",
        "Origen": "España",
        "Actuación_realizada_en_España": "Fabrica",
        "precio_venta": 52.99,
        "alimentacion": "1x 9V",
        "numero_pilas": 1,
        "marca_pilas": "Marca Blanca",
        "tipo_pila": "9V",
        "precio_por_pila": {
            "precio": 1.3,
            "fuente": "Distribuidores OEM y marketplaces nacionales"
        },
        "factor_sulfatacion": {
            "tasa_anual": 0.0125,
            "fuente": "Independent Lab Tests (2023)"
        },
        "desconectable": "No",
        "funda_termica": "No",
        "imagen": "Ledone_Connected.png",
        "fabricante": "Plásticos Erum s.l. Alcoy",
        "origen": "España",
        "titulo_imagen": "Ledone_Connected.png",
        "quality_5": 2.73,
        "value_5": 2.57,
        "imagen_url": "/comparativa-balizas-mvp/client/images/beacons/Ledone_Connected.png",
        "Resistencia": "IP65",
        "Operador": "Telefonica Tech",
        "Piloto_Gps": "No",
        "Aplicación_Móvil": "Si",
        "Fiabilidad": "4.5",
        "Autonomia": "3.0",
        "Conectividad": "4.5",
        "Calidad_Precio": "4.5",
        "funcion_1": "Homologación como V16 Conecta",
        "funcion_2": "con conexión DGT 3.0",
        "funcion_3": "Aplicación Móvil",
        "funcion_4": "Alcance 360º",
        "funcion_5": "resistencia 180Pa",
        "funcion_6": "baterías y magnetismo Imán Nodimio",
        "ventaja_1": "Made in Spain (Ensamblada en Alcoy).",
        "ventaja_2": "Certificado CE",
        "ventaja_3": "Reciclable.",
        "ventaja_4": "Kit Soporte Flecha para Vehículo Industrial y Aseica por 49,95€ con donación de 10€ para lucha contra el cáncer.",
        "ventaja_5": "Pago Seguro, a plazos y con cupones de pago.",
        "inconveniente_2": "No piloto para emitir señal de Geolocalización.",
        "inconveniente_3": "Producto muy endeble",
        "inconveniente_4": "Diseño no apto para guantera",
        "inconveniente_5": "Señal desde la App",
        "inconveniente_6": "No informa Candelas"
    },
    {
        "id_baliza": 19,
        "marca_baliza": "BALIZA3e V-16/SMART MOD100",
        "modelo": "MOD100",
        "Fabricante": "Energía Eléctrica Eficiente, S.L.",
        "Origen": "España",
        "Actuación_realizada_en_España": "Distribución",
        "precio_venta": 59.9,
        "alimentacion": "1x 9V",
        "numero_pilas": 1,
        "marca_pilas": "Sin Marca",
        "tipo_pila": "9V",
        "precio_por_pila": {
            "precio": 0.8,
            "fuente": "AliExpress, Shein, bazares multiprecio"
        },
        "factor_sulfatacion": {
            "tasa_anual": 0.0105,
            "fuente": "Empirical Data from Repair Shops"
        },
        "desconectable": "No",
        "funda_termica": "No",
        "imagen": "BALIZA3e_V-16/SMART_MOD100.png",
        "fabricante": "Energía Eléctrica Eficiente S.L.",
        "origen": "España",
        "titulo_imagen": "BALIZA3e_V-16/SMART_MOD100.png",
        "quality_5": 2.3,
        "value_5": 1.92,
        "imagen_url": "/comparativa-balizas-mvp/client/images/beacons/BALIZA3e_V-16_SMART_MOD100.png",
        "Resistencia": "IP54",
        "Piloto_Gps": "No",
        "Aplicación_Móvil": "No",
        "Fiabilidad": "4.0",
        "Autonomia": "3.5",
        "Conectividad": "3.0",
        "Calidad_Precio": "2.0",
        "funcion_1": "Homologación como V16 Conecta",
        "funcion_2": "con conexión DGT 3.0",
        "funcion_3": "No se especifica ninguna Aplicación Móvil",
        "funcion_4": "Alcance 360º",
        "funcion_5": "resistencia 180Pa",
        "funcion_6": "baterías y magnetismo Imán Nodimio",
        "ventaja_1": "Posibilidad de Comprar con Estuche por 4,95€",
        "ventaja_2": "Extensión de garantía hasta el 2038 dando de alta la baliza",
        "ventaja_3": "Informar hasta 3 números de teléfono movi donde recibir SMS con la ubicación de la baliza.",
        "ventaja_4": "Descactivación de la Baliza en caso de robo.",
        "ventaja_5": "Sujeción sobre superficie lisa con plataforma Sucker3e para Cristal, Aluminio de gran Adherencia por 24,9€",
        "inconveniente_1": "Precios elevados.",
        "inconveniente_2": "No se indica APP",
        "inconveniente_3": "No informa Candelas"
    },
    {
        "id_baliza": 20,
        "marca_baliza": "Car-Lite",
        "modelo": "MOD100",
        "Fabricante": "Energía Eléctrica Eficiente, S.L.",
        "Origen": "España",
        "Actuación_realizada_en_España": "Distribución",
        "precio_venta": 59.9,
        "alimentacion": "1x 9V",
        "numero_pilas": 1,
        "marca_pilas": "Marca Blanca",
        "tipo_pila": "9V",
        "precio_por_pila": {
            "precio": 1.3,
            "fuente": "Distribuidores OEM y marketplaces nacionales"
        },
        "factor_sulfatacion": {
            "tasa_anual": 0.0125,
            "fuente": "Independent Lab Tests (2023)"
        },
        "desconectable": "No",
        "funda_termica": "No",
        "imagen": "Car-Lite.png",
        "fabricante": "Energía Eléctrica Eficiente S.L.",
        "origen": "España",
        "titulo_imagen": "Car-Lite.png",
        "quality_5": 2.73,
        "value_5": 3.41,
        "imagen_url": "/comparativa-balizas-mvp/client/images/beacons/Car-Lite.png",
        "Resistencia": "IP54",
        "Piloto_Gps": "Si",
        "Aplicación_Móvil": "No",
        "Fiabilidad": "3.5",
        "Autonomia": "4.0",
        "Conectividad": "4.0",
        "Calidad_Precio": "3.0",
        "funcion_1": "Homologación como V16 Conecta",
        "funcion_2": "con conexión DGT 3.0 Aplicación Móvil (No Alcance 360º",
        "funcion_3": "resistencia 180Pa",
        "funcion_4": "baterías 9V y magnetismoImán Nodimio",
        "ventaja_1": "Anunciada por el Presentador Calleja.",
        "ventaja_2": "Aviso luminoso de Conexión a la DGT.",
        "ventaja_3": "Informar hasta 3 números de teléfono móvil donde recibir SMS con la ubicación de la baliza.",
        "ventaja_4": "Extensión de garantía hasta el 1 de enero de 2039 dando de alta la baliza.",
        "inconveniente_1": "Precios elevados.",
        "inconveniente_2": "No se indica APP",
        "inconveniente_3": "No informa Candelas"
    },
    {
        "id_baliza": 21,
        "marca_baliza": "Osram LEDguardian V16",
        "modelo": "OSRAM LEDguardian® ROAD FLARE Signal V16 IoT",
        "Fabricante": "Hangzhou Tiger Auto Industry Co., Ltd",
        "Origen": "China",
        "Actuación_realizada_en_España": "Distribución",
        "precio_venta": 51.99,
        "alimentacion": "1x 9V",
        "numero_pilas": 1,
        "marca_pilas": "Marca Blanca",
        "tipo_pila": "9V",
        "precio_por_pila": {
            "precio": 1.3,
            "fuente": "Distribuidores OEM y marketplaces nacionales"
        },
        "factor_sulfatacion": {
            "tasa_anual": 0.0125,
            "fuente": "Independent Lab Tests (2023)"
        },
        "desconectable": "No",
        "funda_termica": "No",
        "imagen": "Osram_LEDguardian_V16.png",
        "fabricante": "Hangzhou Tiger Auto Industry Co. Ltd",
        "origen": "China",
        "titulo_imagen": "Osram_LEDguardian_V16.png",
        "quality_5": 2.53,
        "value_5": 2.43,
        "imagen_url": "/comparativa-balizas-mvp/client/images/beacons/Osram_LEDguardian_V16.png",
        "Resistencia": "IP65",
        "Operador": "Telefonica Tech",
        "Piloto_Gps": "No",
        "Aplicación_Móvil": "No",
        "Fiabilidad": "4.0",
        "Autonomia": "4.0",
        "Conectividad": "4.0",
        "Calidad_Precio": "3.1",
        "funcion_1": "Homologación como V16 Conecta",
        "funcion_2": "con conexión DGT 3.0",
        "funcion_3": "Alcance 360º",
        "funcion_4": "resistencia 180Pa",
        "funcion_5": "baterías y magnetismo Imán Nodimio",
        "ventaja_1": "Indicador de carga de batería en la Baliza",
        "ventaja_2": "Marca líder en el segmento Iluminación.",
        "ventaja_3": "Experiencia de un líder.",
        "inconveniente_1": "Fabricado en China.",
        "inconveniente_2": "No existe aún canal de ventas",
        "inconveniente_3": "política de precios B2B ni B2C.",
        "inconveniente_4": "No mantiene APP activa ni información de stocks ni disponibilidad.",
        "inconveniente_5": "No informa Candelas"
    },
    {
        "id_baliza": 22,
        "marca_baliza": "Geoblueshield49",
        "modelo": "RV7000",
        "Fabricante": "Atressa Global Corporation, S.L., Vizcaya",
        "Origen": "España",
        "Actuación_realizada_en_España": "Fabrica",
        "precio_venta": 54.95,
        "alimentacion": "1x 9V",
        "numero_pilas": 1,
        "marca_pilas": "Energizer",
        "tipo_pila": "9V",
        "precio_por_pila": {
            "precio": 3,
            "fuente": "Amazon, MediaMarkt, Farnell, RS Components"
        },
        "factor_sulfatacion": {
            "tasa_anual": 0.0055,
            "fuente": "Battery University, Duracell Technical Bulletin #45"
        },
        "desconectable": "Si",
        "funda_termica": "Eva foam",
        "imagen": "Geoblueshield49.png",
        "fabricante": "Atressa Global Corporation S.L. Vizcaya",
        "origen": "España",
        "titulo_imagen": "Geoblueshield49.png",
        "quality_5": 5,
        "value_5": 4.55,
        "imagen_url": "/comparativa-balizas-mvp/client/images/beacons/Geoblueshield49.png",
        "Resistencia": "IP54",
        "Operador": "Telefonica Tech",
        "Piloto_Gps": "Si",
        "Aplicación_Móvil": "Si. Propietaria",
        "Fiabilidad": "5.0",
        "Autonomia": "4.9",
        "Conectividad": "4.8",
        "Calidad_Precio": "4.6",
        "funcion_1": "Homologación como V16 Conecta",
        "funcion_2": "con conexión DGT 3.0",
        "funcion_3": "Aplicación Móvil Propietaria",
        "funcion_4": "Alcance 360º",
        "funcion_5": "resistencia 180Pa. Acabados antivandálicos",
        "funcion_6": "baterías y magnetismo Imán Nodimio",
        "funcion_7": "Más de 160 candelas",
        "ventaja_1": "Made in Spain. 0 Dependencia de china",
        "ventaja_2": "Máximas Calidades en todos los materiales: Más de 70 años de experiencia",
        "ventaja_3": "Personalización de la baliza aún para Pedidos Pequeños",
        "ventaja_4": "Incluye Estuche de EVA Foam y posibilidad de desonectar polos",
        "ventaja_5": "Baliza Robusta con acabados únicos.",
        "ventaja_6": "98% material de la carcas reciclados",
        "ventaja_7": "Incluye 6 meses gratis de licencia de sofware Autotekne.",
        "inconveniente_1": "Incorporación tardía al mercado"
    },
    {
        "id_baliza": 23,
        "marca_baliza": "SOS Traffic",
        "modelo": "RV7000",
        "Fabricante": "Atressa Global Corporation, S.L., Vizcaya",
        "Origen": "España",
        "Actuación_realizada_en_España": "Fabrica",
        "precio_venta": 49.95,
        "alimentacion": "1x 9V",
        "numero_pilas": 1,
        "marca_pilas": "Marca Blanca",
        "tipo_pila": "9V",
        "precio_por_pila": {
            "precio": 1.3,
            "fuente": "Distribuidores OEM y marketplaces nacionales"
        },
        "factor_sulfatacion": {
            "tasa_anual": 0.0125,
            "fuente": "Independent Lab Tests (2023)"
        },
        "desconectable": "Si",
        "funda_termica": "No",
        "imagen": "SOS_Traffic.png",
        "fabricante": "Atressa Global Corporation S.L. Vizcaya",
        "origen": "España",
        "titulo_imagen": "SOS_Traffic.png",
        "quality_5": 4.6,
        "value_5": 4.2,
        "imagen_url": "/comparativa-balizas-mvp/client/images/beacons/SOS_Traffic.png",
        "Resistencia": "IP54",
        "Operador": "Teledos",
        "Piloto_Gps": "Si",
        "Aplicación_Móvil": "Si. Propietaria",
        "Fiabilidad": "5.0",
        "Autonomia": "4.9",
        "Conectividad": "4.0",
        "Calidad_Precio": "4.2",
        "funcion_1": "Homologación como V16 Conecta",
        "funcion_2": "con conexión DGT 3.0",
        "funcion_3": "Aplicación Móvil",
        "funcion_4": "Alcance 360º",
        "funcion_5": "resistencia 180Pa",
        "funcion_6": "baterías y magnetismo Imán Nodimio",
        "funcion_7": "Más de 160 candelas",
        "ventaja_1": "Made in Spain",
        "ventaja_2": "Máximas Calidades: Más de 70 años de experiencia",
        "ventaja_3": "Personalización para Pedidos Pequeños",
        "ventaja_4": "Posibilidad de desonectar polos",
        "ventaja_5": "Baliza Robusta con acabados únicos.",
        "ventaja_6": "98% material de la carcas reciclados",
        "ventaja_7": "Incluye Autotekne.",
        "inconveniente_1": "Incorporación tardía al mercado"
    },
    {
        "id_baliza": 24,
        "marca_baliza": "Señal luminosa V16 Toyota",
        "modelo": "Safety Light",
        "Fabricante": "Trafic Safety S.L",
        "Origen": "España",
        "Actuación_realizada_en_España": "Ensamblaje",
        "precio_venta": 49.95,
        "alimentacion": "1x 9V",
        "numero_pilas": 1,
        "marca_pilas": "Sin Marca",
        "tipo_pila": "9V",
        "precio_por_pila": {
            "precio": 0.8,
            "fuente": "AliExpress, Shein, bazares multiprecio"
        },
        "factor_sulfatacion": {
            "tasa_anual": 0.0105,
            "fuente": "Empirical Data from Repair Shops"
        },
        "desconectable": "No",
        "funda_termica": "No",
        "imagen": "Señal_luminosa_V16_Toyota.png",
        "fabricante": "Trafic Safety S.L",
        "origen": "España",
        "titulo_imagen": "Señal_luminosa_V16_Toyota.png",
        "quality_5": 2,
        "value_5": 2.06,
        "imagen_url": "/comparativa-balizas-mvp/client/images/beacons/Señal_luminosa_V16_Toyota.png",
        "Resistencia": "IP65",
        "Operador": "Telefonica Tech",
        "Piloto_Gps": "No",
        "Aplicación_Móvil": "No",
        "Fiabilidad": "4.0",
        "Autonomia": "4.0",
        "Conectividad": "4.0",
        "Calidad_Precio": "3.1",
        "funcion_1": "Homologación como V16 Conecta",
        "funcion_2": "con conexión DGT 3.0",
        "funcion_3": "Alcance 360º",
        "funcion_4": "resistencia 180Pa",
        "funcion_5": "baterías y magnetismo Imán Nodimio"
    },
    {
        "id_baliza": 25,
        "marca_baliza": "KSIX V16 IoT GPS",
        "modelo": "T-912",
        "Fabricante": "Oversunenergy, S.L.",
        "Origen": "España",
        "Actuación_realizada_en_España": "Ensamblaje",
        "precio_venta": 49.9,
        "alimentacion": "1x 9V",
        "numero_pilas": 1,
        "marca_pilas": "Sin Marca",
        "tipo_pila": "9V",
        "precio_por_pila": {
            "precio": 0.8,
            "fuente": "AliExpress, Shein, bazares multiprecio"
        },
        "factor_sulfatacion": {
            "tasa_anual": 0.0105,
            "fuente": "Empirical Data from Repair Shops"
        },
        "desconectable": "No",
        "funda_termica": "No",
        "imagen": "KSIX_V16_IoT_GPS.png",
        "fabricante": "Oversunenergy S.L.",
        "origen": "España",
        "titulo_imagen": "KSIX_V16_IoT_GPS.png",
        "quality_5": 2,
        "value_5": 2.06,
        "imagen_url": "/comparativa-balizas-mvp/client/images/beacons/KSIX_V16_IoT_GPS.png",
        "Resistencia": "IP54",
        "Operador": "Orange",
        "Piloto_Gps": "Si",
        "Aplicación_Móvil": "Si. Propietaria",
        "Fiabilidad": "4.0",
        "Autonomia": "4.0",
        "Conectividad": "3.8",
        "Calidad_Precio": "3.5",
        "funcion_1": "Homologación como V16 Conecta",
        "funcion_2": "con conexión DGT 3.0",
        "funcion_3": "Aplicación Móvil No Integrada",
        "funcion_4": "Alcance 360º",
        "funcion_5": "resistencia 180Pa",
        "funcion_7": "Magnetismo Imán Nodimio",
        "ventaja_1": "Atlantis",
        "ventaja_2": "distribuidor español especializado en la venta de accesorios móviles.",
        "ventaja_3": "B2C bajo registro.",
        "ventaja_4": "Financiación a 12 meses con Sequra.",
        "ventaja_5": "Cupón descuento 10% en primer pedido.",
        "ventaja_6": "Multiples Accesorios.",
        "inconveniente_1": "Versión muy básica de producto.",
        "inconveniente_2": "Precios desposicionado.",
        "inconveniente_3": "Falta de aplicación móvil de respaldo."
    },
    {
        "id_baliza": 26,
        "marca_baliza": "Planet V16",
        "modelo": "V16IoT",
        "Fabricante": "Yuyao Jiming Electronic Co., Ltd",
        "Origen": "China",
        "Actuación_realizada_en_España": "Fabrica",
        "precio_venta": 47.75,
        "alimentacion": "3x AAA",
        "numero_pilas": 3,
        "marca_pilas": "Sin Marca",
        "tipo_pila": "AAA",
        "precio_por_pila": {
            "precio": 0.2,
            "fuente": "AliExpress, Shein, bazares multiprecio"
        },
        "factor_sulfatacion": {
            "tasa_anual": 0.0105,
            "fuente": "User-Reported Failure Rates"
        },
        "desconectable": "No",
        "funda_termica": "No",
        "imagen": "Planet_V16.png",
        "fabricante": "Yuyao Jiming Electronic Co. Ltd",
        "origen": "China",
        "titulo_imagen": "Planet_V16.png",
        "quality_5": 2,
        "value_5": 2.06,
        "imagen_url": "/comparativa-balizas-mvp/client/images/beacons/Planet_V16.png",
        "Resistencia": "IP54",
        "Piloto_Gps": "Si",
        "Aplicación_Móvil": "Si. Propietaria",
        "funcion_1": "Homologación como V16 Conecta",
        "funcion_2": "con conexión DGT 3.0",
        "funcion_3": "Aplicación Móvil",
        "funcion_4": "Alcance 360º",
        "funcion_5": "resistencia 180Pa",
        "funcion_6": "baterías y magnetismo Imán Nodimio"
    },
    {
        "id_baliza": 27,
        "marca_baliza": "SOOS V16",
        "modelo": "V16IoT",
        "Fabricante": "Yuyao Jiming Electronic Co., Ltd",
        "Origen": "China",
        "Actuación_realizada_en_España": "Fabrica",
        "precio_venta": 48.6,
        "alimentacion": "3x AAA",
        "numero_pilas": 3,
        "marca_pilas": "Sin Marca",
        "tipo_pila": "AAA",
        "precio_por_pila": {
            "precio": 0.2,
            "fuente": "AliExpress, Shein, bazares multiprecio"
        },
        "factor_sulfatacion": {
            "tasa_anual": 0.0105,
            "fuente": "User-Reported Failure Rates"
        },
        "desconectable": "No",
        "funda_termica": "No",
        "imagen": "SOOS_V16.png",
        "fabricante": "Yuyao Jiming Electronic Co. Ltd",
        "origen": "China",
        "titulo_imagen": "SOOS_V16.png",
        "quality_5": 2,
        "value_5": 2.06,
        "imagen_url": "/comparativa-balizas-mvp/client/images/beacons/SOOS_V16.png",
        "Resistencia": "IP54",
        "Operador": "Telefonica Tech",
        "Piloto_Gps": "No",
        "Aplicación_Móvil": "No",
        "Fiabilidad": "3.5",
        "Autonomia": "2.8",
        "Conectividad": "3.0",
        "Calidad_Precio": "4.0",
        "funcion_1": "Homologación como V16 Conecta",
        "funcion_2": "con conexión DGT 3.0",
        "funcion_3": "Aplicación Móvil",
        "funcion_4": "Alcance 360º",
        "funcion_5": "resistencia 180Pa",
        "funcion_6": "baterías y magnetismo Imán Nodimio",
        "ventaja_1": "Diferentes métodos de pago.",
        "ventaja_2": "Precio reducido por unidad para 2, 3 y 4 artículos.",
        "ventaja_3": "Política de envios desde c/ Sant Gil 14. Barcelona",
        "inconveniente_1": "Contacto a través de email.",
        "inconveniente_2": "3 pilas AA+. Riesgo Sulfatado"
    },
    {
        "id_baliza": 29,
        "marca_baliza": "SOS Flash V16 Connected EVO",
        "modelo": "BAL/4",
        "Fabricante": "Yuyao Jiming Electronic Co., Ltd",
        "Origen": "China",
        "Actuación_realizada_en_España": "Fabrica",
        "precio_venta": 49.9,
        "alimentacion": "3x AA",
        "numero_pilas": 3,
        "marca_pilas": "Sin Marca",
        "tipo_pila": "AA",
        "precio_por_pila": {
            "precio": 0.28,
            "fuente": "AliExpress, Shein, bazares multiprecio"
        },
        "factor_sulfatacion": {
            "tasa_anual": 0.0105,
            "fuente": "Crowdsourced Device Damage Reports"
        },
        "desconectable": "No",
        "funda_termica": "No",
        "imagen": "SoSflashV16ConnectedEVO.png",
        "fabricante": "Yuyao Jiming Electronic Co. Ltd",
        "origen": "China",
        "titulo_imagen": "SoSflashV16ConnectedEVO.png",
        "quality_5": 2,
        "value_5": 2.06,
        "imagen_url": "/comparativa-balizas-mvp/client/images/beacons/SoSflashV16ConnectedEVO.png",
        "Resistencia": "IP54",
        "Operador": "Telefonica Tech",
        "Piloto_Gps": "Si",
        "Aplicación_Móvil": "Inspide",
        "Fiabilidad": "3.5",
        "Autonomia": "2.8",
        "Conectividad": "4.0",
        "Calidad_Precio": "3.9",
        "funcion_1": "Homologación como V16 Conecta",
        "funcion_2": "con conexión DGT 3.0",
        "funcion_3": "Aplicación Móvil",
        "funcion_4": "Alcance 360º",
        "funcion_5": "resistencia 180Pa",
        "funcion_6": "baterías y magnetismo Imán Nodimio",
        "ventaja_1": "Acceso a todas la balizas a través de Inspide por Whatsapp https://www.sos-flash.com/v16-connected/",
        "ventaja_2": "Soporte Ventosa para Baliza por 5.9€",
        "inconveniente_1": "3 Pilas AA con mayor autonomía pero riesgo deterioro y sulfatación.",
        "inconveniente_2": "Modelo Chino estándar.",
        "inconveniente_3": "Mucho plástico en botones y carcasa",
        "inconveniente_4": "No espefica lúmenes"
    },
    {
        "id_baliza": 28,
        "marca_baliza": "Help Flash IoT+",
        "modelo": "IoT V4",
        "Fabricante": "Kepar Electrónica S. L.",
        "Origen": "España",
        "Actuación_realizada_en_España": "Ensamblaje",
        "precio_venta": 54.95,
        "alimentacion": "1x 9V",
        "numero_pilas": 1,
        "marca_pilas": "Marca Blanca",
        "tipo_pila": "9V",
        "precio_por_pila": {
            "precio": 1.3,
            "fuente": "Distribuidores OEM y marketplaces nacionales"
        },
        "factor_sulfatacion": {
            "tasa_anual": 0.0125,
            "fuente": "Independent Lab Tests (2023)"
        },
        "desconectable": "No",
        "funda_termica": "No",
        "imagen": "Help_Flash_IoT_+.png",
        "fabricante": "Kepar Electrónica S. L.",
        "origen": "España",
        "titulo_imagen": "Help_Flash_IoT_+.png",
        "quality_5": 2,
        "value_5": 2.06,
        "imagen_url": "/comparativa-balizas-mvp/client/images/beacons/Help_Flash_IoT_+.png",
        "Resistencia": "IP54",
        "Operador": "Vodafone",
        "Piloto_Gps": "No",
        "Aplicación_Móvil": "Si",
        "Fiabilidad": "4.5",
        "Autonomia": "4.2",
        "Conectividad": "4.2",
        "Calidad_Precio": "4.0",
        "funcion_1": "Homologación como V16 Conecta",
        "funcion_2": "con conexión DGT 3.0",
        "funcion_3": "Aplicación Móvil",
        "funcion_4": "Alcance 360º",
        "funcion_5": "resistencia 180Pa",
        "funcion_6": "baterías y magnetismo Imán Nodimio",
        "ventaja_1": "Distribuidor solvente español.",
        "ventaja_2": "Extensa Base de Clientes.",
        "ventaja_3": "Recomendado por Ponle Freno.",
        "ventaja_4": "App Gratuita.",
        "ventaja_5": "Ensamblaje en España",
        "ventaja_6": "Más de 200 candelas",
        "inconveniente_1": "Portfolio poco desarrrollado",
        "inconveniente_2": "Buenos apagados combinados con Botones de plástico",
        "inconveniente_3": "Funda de Neopreno opcional incrementando precio",
        "inconveniente_4": "Comparte ensamblaje con muchos modelos en fabrica",
        "inconveniente_5": "Kepar para ensamble de muchas marcas",
        "inconveniente_6": "Muchos compromisos y distribuidores. Descentralización excesiva"
    }
]